casbin_tortoise_adapter-2.0.0.dist-info/METADATA
casbin_tortoise_adapter-2.0.0.dist-info/WHEEL
casbin_tortoise_adapter-2.0.0.dist-info/licenses/LICENSE
casbin_tortoise_adapter/__init__.py
casbin_tortoise_adapter/adapter.py
casbin_tortoise_adapter/filter.py
casbin_tortoise_adapter/model.py
casbin_tortoise_adapter/py.typed
casbin_tortoise_adapter/typing.py
casbin_tortoise_adapter-2.0.0.dist-info/RECORD
