Metadata-Version: 2.1
Name: casbin-tortoise-adapter
Version: 2.0.0
Summary: Tortoise ORM adapter for AsyncCasbin
Keywords: casbin asyncio access control Tortoise ORM authorization pycasbin
Author-Email: Elias Gabriel <me@eliasfgabriel.com>
License: Apache-2.0
Project-URL: Repository, https://github.com/thearchitector/casbin-tortoise-adapter
Project-URL: Documentation, https://github.com/thearchitector/casbin-tortoise-adapter#tortoise-orm-adapter-for-asynccasbin
Project-URL: Changelog, https://github.com/thearchitector/casbin-tortoise-adapter/blob/main/CHANGELOG.md
Requires-Python: <4.0,>=3.7
Requires-Dist: tortoise-orm[accel]>=0.18.0
Requires-Dist: casbin>=1.34.0
